kireji/__init__.py
kireji/__main__.py
kireji-0.1.0.dist-info/METADATA
kireji-0.1.0.dist-info/WHEEL
kireji-0.1.0.dist-info/entry_points.txt
kireji-0.1.0.dist-info/top_level.txt
kireji-0.1.0.dist-info/RECORD
