Metadata-Version: 2.1
Name: kireji
Version: 0.1.0
Summary: A plaintext note-taking CLI in Python.
Author-email: Stephen Malone <mail@wirehaiku.org>
License: BSD-3-Clause
Keywords: note,notes,note-taking,cli
Classifier: Development Status :: 3 - Alpha
Classifier: Environment :: Console
Classifier: Intended Audience :: End Users/Desktop
Classifier: License :: OSI Approved :: BSD License
Classifier: Natural Language :: English
Classifier: Operating System :: POSIX
Classifier: Programming Language :: Python :: 3.10
Classifier: Topic :: Office/Business
Requires-Python: >=3.10
Requires-Dist: click (>=8.1)
